lc_reconstruction_analysis/__init__.py
lc_reconstruction_analysis/axon.py
lc_reconstruction_analysis/clustering.py
lc_reconstruction_analysis/correlation.py
lc_reconstruction_analysis/dendritic.py
lc_reconstruction_analysis/dev.py
lc_reconstruction_analysis/graph.py
lc_reconstruction_analysis/markov.py
lc_reconstruction_analysis/utils.py
lc_reconstruction_analysis/visualization.py
lc_reconstruction_analysis-0.0.24.dist-info/licenses/LICENSE
lc_reconstruction_analysis-0.0.24.dist-info/METADATA
lc_reconstruction_analysis-0.0.24.dist-info/WHEEL
lc_reconstruction_analysis-0.0.24.dist-info/top_level.txt
lc_reconstruction_analysis-0.0.24.dist-info/RECORD
